GearMess_server-0.1.1.dist-info/METADATA
GearMess_server-0.1.1.dist-info/RECORD
GearMess_server-0.1.1.dist-info/WHEEL
GearMess_server-0.1.1.dist-info/entry_points.txt
GearMess_server-0.1.1.dist-info/top_level.txt
server_src/__init__.py
server_src/handlers.py
server_src/models.py
server_src/server.py
server_src/JIM/JIMs.py
server_src/JIM/__init__.py
server_src/JIM/jim_config.py
server_src/crypto/__init__.py
server_src/crypto/crypto.py
